pheader/__init__.py
pheader/__meta__.py
pheader/__version__.py
pheader/pheader.py
pheader-0.24.dist-info/LICENSE.rst
pheader-0.24.dist-info/METADATA
pheader-0.24.dist-info/WHEEL
pheader-0.24.dist-info/entry_points.txt
pheader-0.24.dist-info/top_level.txt
pheader-0.24.dist-info/RECORD
